langgraph_runtime_inmem/__init__.py
langgraph_runtime_inmem/checkpoint.py
langgraph_runtime_inmem/database.py
langgraph_runtime_inmem/inmem_stream.py
langgraph_runtime_inmem/lifespan.py
langgraph_runtime_inmem/metrics.py
langgraph_runtime_inmem/ops.py
langgraph_runtime_inmem/queue.py
langgraph_runtime_inmem/retry.py
langgraph_runtime_inmem/routes.py
langgraph_runtime_inmem/store.py
langgraph_runtime_inmem-0.22.0.dist-info/METADATA
langgraph_runtime_inmem-0.22.0.dist-info/WHEEL
langgraph_runtime_inmem-0.22.0.dist-info/RECORD
